pyconsmenu.py
pyconsmenu-1.0.1.dist-info/WHEEL
pyconsmenu-1.0.1.dist-info/METADATA
pyconsmenu-1.0.1.dist-info/RECORD
