Metadata-Version: 2.1
Name: pyconsmenu
Version: 1.0.1
Summary: Create menu in terminal, guide = youtube.com/watch?v=haSVq3-v1Jk
Author: LON112
Author-email: blonylow@gmail.com
Requires-Python: >=3.7,<4.0
Classifier: Programming Language :: Python :: 3
Classifier: Programming Language :: Python :: 3.10
Classifier: Programming Language :: Python :: 3.7
Classifier: Programming Language :: Python :: 3.8
Classifier: Programming Language :: Python :: 3.9
